ngs_toolkit/__init__.py
ngs_toolkit/_version.py
ngs_toolkit/analysis.py
ngs_toolkit/atacseq.py
ngs_toolkit/chipseq.py
ngs_toolkit/cnv.py
ngs_toolkit/constants.py
ngs_toolkit/decorators.py
ngs_toolkit/exceptions.py
ngs_toolkit/general.py
ngs_toolkit/graphics.py
ngs_toolkit/parsers.py
ngs_toolkit/project_manager.py
ngs_toolkit/rnaseq.py
ngs_toolkit/track_manager.py
ngs_toolkit/utils.py
ngs_toolkit/config/default.yaml
ngs_toolkit/config/example.yaml
ngs_toolkit/demo/__init__.py
ngs_toolkit/demo/data_generator.py
ngs_toolkit/recipes/__init__.py
ngs_toolkit/recipes/call_peaks.py
ngs_toolkit/recipes/coverage.py
ngs_toolkit/recipes/deseq2.py
ngs_toolkit/recipes/enrichr.py
ngs_toolkit/recipes/generate_project.py
ngs_toolkit/recipes/lola.py
ngs_toolkit/recipes/merge_signal.py
ngs_toolkit/recipes/ngs_analysis.py
ngs_toolkit/recipes/region_enrichment.py
ngs_toolkit/recipes/region_set_frip.py
ngs_toolkit/templates/__init__.py
ngs_toolkit/templates/report.html
ngs_toolkit/tests/__init__.py
ngs_toolkit/tests/conftest.py
ngs_toolkit/tests/test_analysis.py
ngs_toolkit/tests/test_atacseq_analysis.py
ngs_toolkit/tests/test_chipseq_analysis.py
ngs_toolkit/tests/test_cnv_analysis.py
ngs_toolkit/tests/test_config.py
ngs_toolkit/tests/test_decorators.py
ngs_toolkit/tests/test_differential_analysis.py
ngs_toolkit/tests/test_differential_enrichment.py
ngs_toolkit/tests/test_general.py
ngs_toolkit/tests/test_install.py
ngs_toolkit/tests/test_logger.py
ngs_toolkit/tests/test_plot_differential.py
ngs_toolkit/tests/test_plot_differential_enrichment.py
ngs_toolkit/tests/test_project_manager.py
ngs_toolkit/tests/test_recipes.py
ngs_toolkit/tests/test_regression_tests.py
ngs_toolkit/tests/test_report.py
ngs_toolkit/tests/test_rnaseq_analysis.py
ngs_toolkit/tests/test_sample_input_files.py
ngs_toolkit/tests/test_unsupervised_analysis.py
ngs_toolkit-0.25.1.data/data/requirements.single_cell.txt
ngs_toolkit-0.25.1.data/data/requirements.test.txt
ngs_toolkit-0.25.1.data/data/requirements.txt
ngs_toolkit-0.25.1.dist-info/LICENCE.txt
ngs_toolkit-0.25.1.dist-info/METADATA
ngs_toolkit-0.25.1.dist-info/WHEEL
ngs_toolkit-0.25.1.dist-info/entry_points.txt
ngs_toolkit-0.25.1.dist-info/top_level.txt
ngs_toolkit-0.25.1.dist-info/RECORD
