Metadata-Version: 2.1
Name: ngs-toolkit
Version: 0.25.1
Summary: A toolkit for NGS analysis with Python.
Home-page: https://github.com/afrendeiro/toolkit
Author: Andre Rendeiro
Author-email: andre.rendeiro@pm.me
License: GPL3
Project-URL: Bug Tracker, https://github.com/afrendeiro/toolkit/issues
Project-URL: Documentation, https://ngs-toolkit.readthedocs.io
Project-URL: Source Code, https://github.com/afrendeiro/toolkit
Keywords: bioinformatics,sequencing,ngs,ngs analysis,ATAC-Seq,ChIP-seq,RNA-seq,project management
Platform: UNKNOWN
Classifier: Programming Language :: Python :: 3 :: Only
Classifier: Programming Language :: Python :: 3.6
Classifier: Programming Language :: Python :: 3.7
Classifier: Programming Language :: Python :: 3.8
Classifier: Development Status :: 4 - Beta
Classifier: License :: OSI Approved :: GNU General Public License v3 or later (GPLv3+)
Classifier: Topic :: Scientific/Engineering :: Bio-Informatics
Requires-Dist: setuptools-scm (>=3.3.3)
Requires-Dist: numpy (>=1.15.0)
Requires-Dist: scipy (>=1.0.0)
Requires-Dist: fastcluster
Requires-Dist: pandas (>=0.25.0)
Requires-Dist: matplotlib
Requires-Dist: seaborn (>=0.10.0)
Requires-Dist: parmap (>=1.5.1)
Requires-Dist: pysam (>=0.13)
Requires-Dist: pybedtools (>=0.7.10)
Requires-Dist: scikit-learn (>=0.19.1)
Requires-Dist: statsmodels (>=0.8.0)
Requires-Dist: patsy (>=0.4.1)
Requires-Dist: tqdm (>=4.19.5)
Requires-Dist: peppy (>=0.30.1)
Requires-Dist: divvy (>=0.5.0)
Requires-Dist: attmap (>=0.12.11)
Requires-Dist: requests (>=2.21.0)
Requires-Dist: jinja2 (>=2.10.1)
Requires-Dist: natsort (>=6.0.0)
Requires-Dist: joblib (>=0.12.5)
Provides-Extra: docs
Requires-Dist: Sphinx ; extra == 'docs'
Requires-Dist: sphinx-rtd-theme ; extra == 'docs'
Requires-Dist: sphinx-issues ; extra == 'docs'
Requires-Dist: sphinx-argparse ; extra == 'docs'
Provides-Extra: single_cell
Requires-Dist: scanpy ; extra == 'single_cell'
Requires-Dist: scanorama ; extra == 'single_cell'
Requires-Dist: phate ; extra == 'single_cell'
Requires-Dist: scvelo ; extra == 'single_cell'
Requires-Dist: loompy ; extra == 'single_cell'
Requires-Dist: fbpca ; extra == 'single_cell'
Requires-Dist: MulticoreTSNE ; extra == 'single_cell'
Requires-Dist: python-igraph ; extra == 'single_cell'
Requires-Dist: louvain (>=0.6) ; extra == 'single_cell'
Requires-Dist: leidenalg ; extra == 'single_cell'
Requires-Dist: fa2 ; extra == 'single_cell'
Provides-Extra: testing
Requires-Dist: pytest (>=4.4.0) ; extra == 'testing'
Requires-Dist: coverage (>=4.5.2) ; extra == 'testing'
Requires-Dist: pytest-cov ; extra == 'testing'
Requires-Dist: codecov ; extra == 'testing'
Requires-Dist: codacy-coverage ; extra == 'testing'
Requires-Dist: pytest-xdist ; extra == 'testing'
Requires-Dist: rpy2 (>=3.2.0) ; extra == 'testing'
